Workbook

Sheet 项目成本汇总
A1: 项目成本汇总表
A2: 单位：人民币元
A4: 序号 | B4: 工种 | C4: 内部成本 | D4: 外包成本 | E4: 总成本 | F4: 内部占比 | G4: 外包占比 | H4: 备注
A5: 1 | B5: 角色原画 | C5: =SUMIF(内部人员成本!B:B,B5,内部人员成本!G:G) -> 149736.31 | D5: =SUMIF(外包成本明细!B:B,B5,外包成本明细!F:F) -> 9600 | E5: =C5+D5 -> 159336.31 | F5: =IFERROR(C5/E5,0) -> 0.93975008 | G5: =IFERROR(D5/E5,0) -> 0.060249922 | H5: 1个中级 2个初级
A6: 2 | B6: 拆图 | C6: =SUMIF(内部人员成本!B:B,B6,内部人员成本!G:G) -> 32625.287 | D6: =SUMIF(外包成本明细!B:B,B6,外包成本明细!F:F) -> 0 | E6: =C6+D6 -> 32625.287 | F6: =IFERROR(C6/E6,0) -> 1 | G6: =IFERROR(D6/E6,0) -> 0 | H6: 计件
A7: 3 | B7: 动作 | C7: =SUMIF(内部人员成本!B:B,B7,内部人员成本!G:G) -> 144873.54 | D7: =SUMIF(外包成本明细!B:B,B7,外包成本明细!F:F) -> 24600 | E7: =C7+D7 -> 169473.54 | F7: =IFERROR(C7/E7,0) -> 0.8548446 | G7: =IFERROR(D7/E7,0) -> 0.1451554 | H7: 1个中级，外包初级7.8人
A8: 4 | B8: 战斗特效 | C8: =SUMIF(内部人员成本!B:B,B8,内部人员成本!G:G) -> 87226.362 | D8: =SUMIF(外包成本明细!B:B,B8,外包成本明细!F:F) -> 9900 | E8: =C8+D8 -> 97126.362 | F8: =IFERROR(C8/E8,0) -> 0.89807093 | G8: =IFERROR(D8/E8,0) -> 0.10192907 | H8: 2个中级，外包初级
A9: 5 | B9: 场景原画 | C9: =SUMIF(内部人员成本!B:B,B9,内部人员成本!G:G) -> 90949.152 | D9: =SUMIF(外包成本明细!B:B,B9,外包成本明细!F:F) -> 0 | E9: =C9+D9 -> 90949.152 | F9: =IFERROR(C9/E9,0) -> 1 | G9: =IFERROR(D9/E9,0) -> 0 | H9: 2个中级
A10: 6 | B10: 地编 | C10: =SUMIF(内部人员成本!B:B,B10,内部人员成本!G:G) -> 11724.138 | D10: =SUMIF(外包成本明细!B:B,B10,外包成本明细!F:F) -> 0 | E10: =C10+D10 -> 11724.138 | F10: =IFERROR(C10/E10,0) -> 1 | G10: =IFERROR(D10/E10,0) -> 0 | H10: 1个中级
A11: 7 | B11: UI | C11: =SUMIF(内部人员成本!B:B,B11,内部人员成本!G:G) -> 148933.48 | D11: =SUMIF(外包成本明细!B:B,B11,外包成本明细!F:F) -> 0 | E11: =C11+D11 -> 148933.48 | F11: =IFERROR(C11/E11,0) -> 1 | G11: =IFERROR(D11/E11,0) -> 0 | H11: 中级1初级，外包中级初级
A12: 8 | B12: 图标设计 | C12: =SUMIF(内部人员成本!B:B,B12,内部人员成本!G:G) -> 36171.034 | D12: =SUMIF(外包成本明细!B:B,B12,外包成本明细!F:F) -> 2400 | E12: =C12+D12 -> 38571.034 | F12: =IFERROR(C12/E12,0) -> 0.93777714 | G12: =IFERROR(D12/E12,0) -> 0.062222858 | H12: 1个中级，外包初级
A13: 9 | B13: UI动效 | C13: =SUMIF(内部人员成本!B:B,B13,内部人员成本!G:G) -> 61082.271 | D13: =SUMIF(外包成本明细!B:B,B13,外包成本明细!F:F) -> 0 | E13: =C13+D13 -> 61082.271 | F13: =IFERROR(C13/E13,0) -> 1 | G13: =IFERROR(D13/E13,0) -> 0 | H13: 1个初级
B14: 合计 | C14: =SUM(C5:C13) -> 763321.57 | D14: =SUM(D5:D13) -> 46500 | E14: =SUM(E5:E13) -> 809821.57 | F14: =IFERROR(C14/E14,0) -> 0.94257994 | G14: =IFERROR(D14/E14,0) -> 0.057420056
A17: 成本结构分析
B18: 内部人力成本占比 | C18: =C14/E14 -> 0.94257994
B19: 外包成本占比 | C19: =D14/E14 -> 0.057420056
B20: 人均日成本（内部） | C20: =IFERROR(C14/SUM(内部人员成本!F:F),0) -> 214.64046
B21: 人均日成本（外包） | C21: =IFERROR(D14/SUM(外包成本明细!E:E),0) -> 180.23256

Sheet 内部人员成本
A1: 内部人员成本明细表
A2: 蓝色字体为可修改的输入项，黑色为公式计算结果
A4: 序号 | B4: 工种 | C4: 人员级别 | D4: 月薪（元） | E4: 日薪（元） | F4: 投入人日 | G4: 人力成本（元） | H4: 备注
A5: 1 | B5: 角色原画 | C5: 中级 | D5: 13347.22 | E5: 613.67 | F5: 242.9 | G5: =E5*F5 -> 149060.44 | H5: 9人
A6: 2 | B6: 角色原画 | C6: 初级 | D6: 3000 | E6: =D6/参数设置!$C$7 -> 137.93103 | F6: 4.9 | G6: =E6*F6 -> 675.86207 | H6: 1人
A7: 3 | B7: 动作 | C7: 初级 | D7: 4750 | E7: =D7/参数设置!$C$7 -> 218.3908 | F7: 136 | G7: =E7*F7 -> 29701.149 | H7: 6人
B8: 动作 | C8: 中级 | D8: 11597.22 | E8: =D8/参数设置!$C$7 -> 533.20552 | F8: 216 | G8: =E8*F8 -> 115172.39 | H8: 9人
A9: 4 | B9: 战斗特效 | C9: 中级 | D9: 15500 | E9: =D9/参数设置!$C$7 -> 712.64368 | F9: 44 | G9: =E9*F9 -> 31356.322 | H9: 2人
B10: 战斗特效 | C10: 初级 | D10: 5486.11 | E10: =D10/参数设置!$C$7 -> 252.23494 | F10: 221.5 | G10: =E10*F10 -> 55870.04 | H10: 9人
A11: 5 | B11: 场景原画 | C11: 初级 | D11: 0 | E11: =D11/参数设置!$C$7 -> 0 | F11: 0 | G11: =E11*F11 -> 0 | H11: 0
B12: 场景原画 | C12: 中级 | D12: 15334.45 | E12: =D12/参数设置!$C$7 -> 705.03218 | F12: 129 | G12: =E12*F12 -> 90949.152 | H12: 2人
A13: 6 | B13: 地编 | C13: 中级 | D13: 15000 | E13: =D13/参数设置!$C$7 -> 689.65517 | F13: 17 | G13: =E13*F13 -> 11724.138 | H13: 1人（暂未投入）
A14: 7 | B14: UI | C14: 中级 | D14: 14375 | E14: =D14/参数设置!$C$7 -> 660.91954 | F14: 129.55 | G14: =E14*F14 -> 85622.126 | H14: 4
A15: 8 | B15: UI | C15: 初级 | D15: 5187.5 | E15: =D15/参数设置!$C$7 -> 238.50575 | F15: 265.45 | G15: =E15*F15 -> 63311.351 | H15: 1人
A16: 9 | B16: 图标设计 | C16: 中级 | D16: 8000 | E16: =D16/参数设置!$C$7 -> 367.81609 | F16: 98.34 | G16: =E16*F16 -> 36171.034 | H16: 1人
A17: 10 | B17: UI动效 | C17: 初级 | D17: 4471.88 | E17: =D17/参数设置!$C$7 -> 205.60368 | F17: 128.4 | G17: =E17*F17 -> 26399.512 | H17: 8人
B18: UI动效 | C18: 中级 | D18: 13375 | E18: =D18/参数设置!$C$7 -> 614.94253 | F18: 56.4 | G18: =E18*F18 -> 34682.759 | H18: 4人
A19: 11 | B19: 拆图 | C19: 初级 | D19: 8000 | E19: =D19/参数设置!$C$7 -> 367.81609 | F19: 88.7 | G19: =E19*F19 -> 32625.287 | H19: 计件辅助
B20: 合计 | F20: =SUM(F5:F19) -> 1778.14 | G20: =SUM(G5:G19) -> 763321.57
A22: 福利与管理费用分摊
B23: 人力成本小计 | G23: =G20 -> 763321.57
B24: 福利费用比例 | G24: =参数设置!$C$8 -> 0.25
B25: 福利费用 | G25: =G20*参数设置!$C$8 -> 190830.39
B26: 管理费用比例 | G26: =参数设置!$C$9 -> 0.15
B27: 管理费用 | G27: =G20*参数设置!$C$9 -> 114498.24
B28: 内部人员总成本 | G28: =G20*(1+参数设置!$C$8+参数设置!$C$9) -> 1068650.2

Sheet 外包成本明细
A1: 外包成本明细表
A2: 蓝色字体为可修改的输入项，黑色为公式计算结果
A4: 序号 | B4: 工种 | C4: 人员级别 | D4: 人日单价（元） | E4: 投入人日 | F4: 外包成本（元） | G4: 供应商/备注
A5: 1 | B5: 角色原画 | C5: 初级 | D5: 1600 | E5: 6 | F5: =D5*E5 -> 9600 | G5: 计件外包
A6: 2 | B6: 拆图 | C6: 计件 | D6: 0 | E6: 0 | F6: =D6*E6 -> 0 | G6: 按件计费
A7: 3 | B7: 动作 | C7: 初级 | D7: 300 | E7: 82 | F7: =D7*E7 -> 24600
A8: 4 | B8: 战斗特效 | C8: 初级 | D8: 300 | E8: 33 | F8: =D8*E8 -> 9900 | G8: 外包初级
A9: 5 | B9: 场景原画 | C9: 初级 | D9: 0 | E9: 0 | F9: =D9*E9 -> 0 | G9: 外包初级
A10: 6 | B10: UI | C10: 中级 | D10: 0 | E10: 0 | F10: =D10*E10 -> 0 | G10: 外包中级
A11: 7 | B11: UI | C11: 初级 | D11: 0 | E11: 0 | F11: =D11*E11 -> 0 | G11: 外包初级
A12: 8 | B12: 图标设计 | C12: 初级 | D12: 300 | E12: 8 | F12: =D12*E12 -> 2400 | G12: 外包初级
A13: 9 | B13: UI动效 | C13: 初级 | D13: 0 | E13: 0 | F13: =D13*E13 -> 0 | G13: 暂无外包
B14: 合计 | E14: =SUM(E5:E13) -> 129 | F14: =SUM(F5:F13) -> 46500
A16: 外包管理费用
B17: 外包成本小计 | F17: =F14 -> 46500
B18: 外包管理费率 | F18: =参数设置!$C$10 -> 0.05
B19: 外包管理费用 | F19: =F14*参数设置!$C$10 -> 2325
B20: 外包总成本 | F20: =F14*(1+参数设置!$C$10) -> 48825

Sheet 参数设置
A1: 参数设置
A2: 蓝色字体为可修改的参数，修改后所有相关计算自动更新
A4: 基础参数
B5: 项目名称 | C5: 游戏美术项目 | D5: 可修改为实际项目名称
B6: 计算日期 | C6: =TODAY() -> 46210 | D6: 自动获取当前日期
B7: 月工作日 | C7: 21.75 | D7: 法定月平均工作日，用于日薪计算
B8: 福利费用比例 | C8: 0.25 | D8: 社保、公积金、福利等占工资比例
B9: 管理费用比例 | C9: 0.15 | D9: 公司管理费用分摊比例
B10: 外包管理费率 | C10: 0.05 | D10: 外包项目管理费用比例
A13: 参考薪资标准（可根据实际情况调整）
A14: 人员级别 | B14: 参考月薪范围 | C14: 参考日薪范围 | D14: 说明
A15: 高级 | B15: 25000-40000 | C15: 1149-1839 | D15: 资深/专家级
A16: 中级 | B16: 15000-25000 | C16: 690-1149 | D16: 有3-5年经验
A17: 初级 | B17: 8000-15000 | C17: 368-690 | D17: 1-3年经验
A18: 实习生 | B18: 4000-8000 | C18: 184-368 | D18: 在校/刚毕业
A20: 使用说明
A21: 1. 在「内部人员成本」表中录入内部人员的工种、级别、月薪和投入人日
A22: 2. 在「外包成本明细」表中录入外包人员的工种、级别、单价和投入人日
A23: 3. 「项目成本汇总」表会自动汇总各工种的内部和外包成本
A24: 4. 可在「参数设置」表中调整工作日、福利比例等参数
A25: 5. 所有蓝色字体的单元格都是可以修改的输入项
A26: 6. 黑色字体为公式计算结果，请勿手动修改
